odoo/addons/duplicate_project_task_timesheet/README.rst
odoo/addons/duplicate_project_task_timesheet/__init__.py
odoo/addons/duplicate_project_task_timesheet/__manifest__.py
odoo/addons/duplicate_project_task_timesheet/readme/CONFIGURE.rst
odoo/addons/duplicate_project_task_timesheet/readme/CONTRIBUTORS.rst
odoo/addons/duplicate_project_task_timesheet/readme/DESCRIPTION.rst
odoo/addons/duplicate_project_task_timesheet/readme/USAGE.rst
odoo/addons/duplicate_project_task_timesheet/static/description/icon.png
odoo/addons/duplicate_project_task_timesheet/static/description/index.html
odoo/addons/duplicate_project_task_timesheet/tests/__init__.py
odoo/addons/duplicate_project_task_timesheet/tests/test_duplicate_project_task_timesheet.py
odoo/addons/duplicate_project_task_timesheet/views/project_views.xml
odoo_addon_duplicate_project_task_timesheet-16.0.1.0.0.dist-info/METADATA
odoo_addon_duplicate_project_task_timesheet-16.0.1.0.0.dist-info/WHEEL
odoo_addon_duplicate_project_task_timesheet-16.0.1.0.0.dist-info/top_level.txt
odoo_addon_duplicate_project_task_timesheet-16.0.1.0.0.dist-info/RECORD
